vinayak/__init__.py
vinayak-0.0.2.dist-info/METADATA
vinayak-0.0.2.dist-info/RECORD
vinayak-0.0.2.dist-info/WHEEL
vinayak-0.0.2.dist-info/top_level.txt
