Metadata-Version: 2.1
Name: vinayak
Version: 0.0.2
Summary: Just a project
Home-page: https://github.com/vinayak-kaniyarakkal/vinayak
Author: Vinayak Kaniyarakkal
Author-email: vinayak.programmer@gmail.com
License: UNKNOWN
Platform: UNKNOWN
Classifier: Programming Language :: Python :: 2
Classifier: License :: OSI Approved :: MIT License
Classifier: Operating System :: OS Independent
